pyggdrasil/__init__.py
pyggdrasil-0.1.1.dist-info/LICENSE.md
pyggdrasil-0.1.1.dist-info/METADATA
pyggdrasil-0.1.1.dist-info/WHEEL
pyggdrasil-0.1.1.dist-info/RECORD
