Metadata-Version: 2.1
Name: pyggdrasil
Version: 0.1.1
Summary: A tiny library to print trees
Author: Jonathan Herrera
Author-email: jonathan.herrera@posteo.de
Requires-Python: >=3.12,<4.0
Classifier: Programming Language :: Python :: 3
Classifier: Programming Language :: Python :: 3.12
